seaborn_image/__init__.py
seaborn_image/_colormap.py
seaborn_image/_context.py
seaborn_image/_core.py
seaborn_image/_datasets.py
seaborn_image/_filters.py
seaborn_image/_general.py
seaborn_image/_grid.py
seaborn_image/utils.py
seaborn_image-0.10.0.dist-info/LICENSE.txt
seaborn_image-0.10.0.dist-info/METADATA
seaborn_image-0.10.0.dist-info/WHEEL
seaborn_image-0.10.0.dist-info/RECORD
