Metadata-Version: 2.1
Name: seaborn-image
Version: 0.10.0
Summary: Attractive, descriptive and effective image visualization with seaborn-like API built on top of matplotlib
Home-page: https://github.com/SarthakJariwala/seaborn-image
License: MIT
Author: Sarthak Jariwala
Author-email: contact@sarthakjariwala.com
Requires-Python: >=3.9,<3.13
Classifier: Framework :: Matplotlib
Classifier: License :: OSI Approved :: MIT License
Classifier: Programming Language :: Python :: 3
Classifier: Programming Language :: Python :: 3.9
Classifier: Programming Language :: Python :: 3.10
Classifier: Programming Language :: Python :: 3.11
Classifier: Programming Language :: Python :: 3.12
Classifier: Topic :: Scientific/Engineering :: Image Processing
Classifier: Topic :: Scientific/Engineering :: Visualization
Requires-Dist: matplotlib (>=3.2.2)
Requires-Dist: matplotlib-scalebar (>=0.7.0,<0.9.0)
Requires-Dist: numpy (>=1.26)
Requires-Dist: palettable (>=3.3.0)
Requires-Dist: pooch (>=1.2.0)
Requires-Dist: scikit-image (>=0.17.2)
Requires-Dist: scipy (>=1.5.1)
Project-URL: Documentation, https://seaborn-image.readthedocs.io/
Project-URL: Repository, https://github.com/SarthakJariwala/seaborn-image
